LeCrunch3/LeCrunch3.py
LeCrunch3/__init__.py
lecrunch3-3.0.3.dist-info/licenses/LICENSE
lecrunch3-3.0.3.dist-info/METADATA
lecrunch3-3.0.3.dist-info/WHEEL
lecrunch3-3.0.3.dist-info/top_level.txt
lecrunch3-3.0.3.dist-info/RECORD
