Metadata-Version: 2.4
Name: LeCrunch3
Version: 3.0.3
Summary: A Python tool to control a LeCroy scope and to acquire/process data
Author-email: Anthony LaTorre <tlatorre9@gmail.com>, Benjamin Land <benland100@gmail.com>, Nicola Minafra <nicola@cern.ch>
License:                     GNU GENERAL PUBLIC LICENSE
Project-URL: Homepage, https://github.com/nminafra/LeCrunch3
Keywords: lecroy,oscilloscope,waveform
Classifier: License :: OSI Approved :: GNU General Public License v3 (GPLv3)
Classifier: Programming Language :: Python
Classifier: Programming Language :: Python :: 3
Classifier: Topic :: Scientific/Engineering :: Information Analysis
Requires-Python: >=3.1
License-File: LICENSE
Requires-Dist: numpy
Provides-Extra: dev
Requires-Dist: black; extra == "dev"
Requires-Dist: bumpver; extra == "dev"
Requires-Dist: isort; extra == "dev"
Requires-Dist: pip-tools; extra == "dev"
Requires-Dist: pytest; extra == "dev"
Dynamic: license-file
